{"version": "BOHEMIA_SEWER_DEMO_MAP_DATA_v1", "built": "2026-07-10", "grid_size": [14, 30], "zones": {"wash": "sewer_wash", "sewer": "sewer_floor", "water": "sewer_water"}, "wall_category": "sewer_wall", "door_category": "sewer_door", "grid": [["void", "wash", "wash", "wash", "wash", "wash", "wash", "water", "wash", "wash", "wash", "wash", "wash", "void"], ["void", "wash", "wash", "wash", "wash", "wash", "wash", "water", "wash", "wash", "wash", "wash", "wash", "void"], ["void", "wash", "wash", "wash", "wash", "wash", "wash", "water", "wash", "wash", "wash", "wash", "wash", "void"], ["void", "wash", "wash", "wash", "wash", "wash", "wash", "water", "wash", "wash", "wash", "wash", "wash", "void"], ["void", "wash", "wash", "wash", "wash", "wash", "wash", "water", "wash", "wash", "wash", "wash", "wash", "void"], ["void", "wash", "wash", "wash", "wash", "wash", "wash", "water", "wash", "wash", "wash", "wash", "wash", "void"], ["void", "wash", "wash", "wash", "wash", "wash", "wash", "water", "wash", "wash", "wash", "wash", "wash", "void"], ["void", "void", "wash", "wash", "wash", "wash", "wash", "wash", "wash", "wash", "wash", "wash", "void", "void"], ["void", "void", "void", "sewer", "sewer", "sewer", "sewer", "sewer", "sewer", "sewer", "sewer", "void", "void", "void"], ["void", "void", "void", "void", "sewer", "sewer", "sewer", "sewer", "sewer", "sewer", "void", "void", "void", "void"], ["void", "void", "void", "void", "void", "void", "sewer", "sewer", "water", "sewer", "sewer", "void", "void", "void"], ["void", "void", "void", "void", "void", "void", "void", "sewer", "sewer", "water", "sewer", "sewer", "void", "void"], ["void", "void", "void", "void", "void", "void", "void", "void", "sewer", "sewer", "water", "sewer", "sewer", "void"], ["void", "void", "void", "void", "void", "void", "void", "void", "sewer", "sewer", "water", "sewer", "sewer", "void"], ["void", "sewer", "sewer", "sewer", "void", "void", "void", "void", "sewer", "sewer", "water", "sewer", "sewer", "void"], ["void", "sewer", "sewer", "sewer", "void", "void", "void", "void", "sewer", "sewer", "water", "sewer", "sewer", "void"], ["void", "sewer", "sewer", "sewer", "void", "void", "void", "void", "sewer", "sewer", "water", "sewer", "sewer", "void"], ["void", "sewer", "sewer", "sewer", "void", "void", "void", "sewer", "sewer", "water", "sewer", "sewer", "void", "void"], ["void", "void", "void", "void", "void", "void", "void", "void", "sewer", "sewer", "water", "sewer", "sewer", "void"], ["void", "void", "void", "void", "void", "void", "void", "void", "sewer", "sewer", "sewer", "sewer", "sewer", "void"], ["void", "void", "void", "void", "void", "void", "void", "void", "sewer", "sewer", "sewer", "sewer", "sewer", "void"], ["void", "void", "void", "void", "void", "void", "void", "sewer", "sewer", "water", "sewer", "sewer", "sewer", "void"], ["void", "void", "void", "void", "void", "void", "sewer", "sewer", "water", "sewer", "sewer", "sewer", "sewer", "void"], ["void", "void", "void", "void", "void", "void", "void", "sewer", "sewer", "water", "sewer", "sewer", "void", "void"], ["void", "void", "void", "void", "void", "void", "void", "void", "sewer", "sewer", "water", "sewer", "sewer", "void"], ["void", "void", "sewer", "sewer", "sewer", "sewer", "sewer", "sewer", "sewer", "sewer", "sewer", "sewer", "void", "void"], ["void", "void", "sewer", "sewer", "sewer", "sewer", "sewer", "sewer", "sewer", "sewer", "sewer", "sewer", "void", "void"], ["void", "void", "sewer", "sewer", "sewer", "sewer", "sewer", "sewer", "sewer", "sewer", "sewer", "sewer", "void", "void"], ["void", "void", "sewer", "sewer", "sewer", "sewer", "sewer", "sewer", "sewer", "sewer", "sewer", "sewer", "void", "void"], ["void", "void", "sewer", "sewer", "sewer", "sewer", "sewer", "sewer", "sewer", "sewer", "sewer", "sewer", "void", "void"]], "walls": [[0, 0], [13, 0], [0, 1], [13, 1], [0, 2], [13, 2], [0, 3], [13, 3], [0, 4], [13, 4], [0, 5], [13, 5], [0, 6], [13, 6], [1, 7], [12, 7], [2, 8], [11, 8], [3, 9], [10, 9], [4, 10], [5, 10], [11, 10], [6, 11], [12, 11], [7, 12], [13, 12], [1, 13], [2, 13], [3, 13], [7, 13], [13, 13], [0, 14], [4, 14], [7, 14], [13, 14], [0, 15], [4, 15], [7, 15], [13, 15], [0, 16], [4, 16], [7, 16], [13, 16], [0, 17], [4, 17], [6, 17], [12, 17], [1, 18], [2, 18], [3, 18], [7, 18], [13, 18], [7, 19], [13, 19], [7, 20], [13, 20], [6, 21], [13, 21], [5, 22], [13, 22], [6, 23], [12, 23], [2, 24], [3, 24], [4, 24], [5, 24], [6, 24], [7, 24], [13, 24], [1, 25], [12, 25], [1, 26], [12, 26], [1, 27], [12, 27], [1, 28], [12, 28], [1, 29], [12, 29]], "player_start": [7, 1], "hatch": {"pos": [7, 27], "note": "THE purple prop. Amalgam colors 196,84,160 / 122,42,96. Art PENDING Paolo."}, "spawns": [{"id": "amb_left_1", "type": "agent", "pos": [2, 15], "note": "left chamber ambush"}, {"id": "amb_left_2", "type": "agent", "pos": [2, 16], "note": "left chamber ambush"}, {"id": "amb_right_1", "type": "agent", "pos": [11, 20], "note": "right chamber ambush"}, {"id": "amb_right_2", "type": "agent", "pos": [12, 21], "note": "right chamber ambush"}, {"id": "hatch_guard_1", "type": "agent", "pos": [5, 27], "note": "hatch room guard"}, {"id": "hatch_guard_2", "type": "agent", "pos": [9, 27], "note": "hatch room guard"}], "laws": ["purple: hatch+agents only", "no volcano tiles", "brightness descends wash->sewer", "modern sewer canon: no beds, gates rare, contemporary props only"], "props": [{"kind": "trash", "pos": [1, 15]}, {"kind": "trash", "pos": [1, 16]}, {"kind": "trash", "pos": [3, 14]}, {"kind": "trash", "pos": [2, 17]}, {"kind": "misc", "pos": [3, 17]}, {"kind": "trash", "pos": [12, 20]}, {"kind": "trash", "pos": [10, 19]}, {"kind": "trash", "pos": [11, 22]}, {"kind": "misc", "pos": [10, 22]}, {"kind": "trash", "pos": [3, 26]}, {"kind": "trash", "pos": [10, 26]}, {"kind": "trash", "pos": [2, 29]}, {"kind": "trash", "pos": [11, 29]}, {"kind": "misc", "pos": [11, 22]}, {"kind": "misc", "pos": [12, 20]}, {"kind": "misc", "pos": [11, 19]}, {"kind": "misc", "pos": [10, 21]}, {"kind": "trash", "pos": [3, 15]}, {"kind": "trash", "pos": [11, 17]}, {"kind": "trash", "pos": [12, 14]}, {"kind": "trash", "pos": [12, 4]}, {"kind": "trash", "pos": [5, 0]}, {"kind": "trash", "pos": [10, 5]}], "prop_pools": {"bed": [{"file": "BOHEMIA_HD_TILE_REPO_part1.txt", "pack": "Barrels, crates and sacks", "idx": 31, "fp": "1x1"}, {"file": "BOHEMIA_HD_TILE_REPO_part1.txt", "pack": "Barrels, crates and sacks", "idx": 35, "fp": "1x1"}, {"file": "BOHEMIA_HD_TILE_REPO_part1.txt", "pack": "Barrels, crates and sacks", "idx": 33, "fp": "1x1"}, {"file": "BOHEMIA_HD_TILE_REPO_part2.txt", "pack": "13. Garden beds", "idx": 29, "fp": "2x1"}, {"file": "BOHEMIA_HD_TILE_REPO_part2.txt", "pack": "13. Garden beds", "idx": 9, "fp": "2x1"}, {"file": "BOHEMIA_HD_TILE_REPO_part2.txt", "pack": "13. Garden beds", "idx": 49, "fp": "2x1"}], "trash": [{"file": "BOHEMIA_HD_TILE_REPO_part2.txt", "pack": "14. Trash and junk props", "idx": 8, "fp": "1x1"}, {"file": "BOHEMIA_HD_TILE_REPO_part2.txt", "pack": "14. Trash and junk props", "idx": 2, "fp": "1x2"}, {"file": "BOHEMIA_HD_TILE_REPO_part2.txt", "pack": "7. Trash and debris", "idx": 0, "fp": "2x2"}, {"file": "BOHEMIA_HD_TILE_REPO_part2.txt", "pack": "14. Trash and junk props", "idx": 7, "fp": "1x1"}, {"file": "BOHEMIA_HD_TILE_REPO_part2.txt", "pack": "14. Trash and junk props", "idx": 5, "fp": "2x1"}, {"file": "BOHEMIA_HD_TILE_REPO_part2.txt", "pack": "7. Trash and debris", "idx": 16, "fp": "2x2"}], "crate": [{"file": "BOHEMIA_HD_TILE_REPO_part3.txt", "pack": "Barrels, crates and objects", "idx": 13, "fp": "1x1"}, {"file": "BOHEMIA_HD_TILE_REPO_part2.txt", "pack": "Containers and items", "idx": 60, "fp": "1x1"}, {"file": "BOHEMIA_HD_TILE_REPO_part2.txt", "pack": "Containers and items", "idx": 35, "fp": "1x1"}, {"file": "BOHEMIA_HD_TILE_REPO_part4.txt", "pack": "8. Toxic waste and barrels", "idx": 1, "fp": "1x1"}, {"file": "BOHEMIA_HD_TILE_REPO_part3.txt", "pack": "Barrels, crates and objects", "idx": 17, "fp": "1x1"}, {"file": "BOHEMIA_HD_TILE_REPO_part3.txt", "pack": "Barrels, crates and objects", "idx": 23, "fp": "2x2"}], "misc": [{"file": "BOHEMIA_HD_TILE_REPO_part4.txt", "pack": "17. Cannons and weapons", "idx": 8, "fp": "2x1"}, {"file": "BOHEMIA_HD_TILE_REPO_part4.txt", "pack": "Jars, pots and urns", "idx": 37, "fp": "1x1"}, {"file": "BOHEMIA_HD_TILE_REPO_part4.txt", "pack": "17. Cannons and weapons", "idx": 6, "fp": "1x1"}, {"file": "BOHEMIA_HD_TILE_REPO_part4.txt", "pack": "Jars, pots and urns", "idx": 31, "fp": "1x1"}, {"file": "BOHEMIA_HD_TILE_REPO_part4.txt", "pack": "Jars, pots and urns", "idx": 14, "fp": "1x1"}, {"file": "BOHEMIA_HD_TILE_REPO_part4.txt", "pack": "Jars, pots and urns", "idx": 17, "fp": "1x1"}]}}